[{"key":"fr","value":"1PMyQ4YIXqlcYHpe8.AWVlBphkuKR-Bbsplvl-cYfqYBU.Bcemm0.NV.AAA.0.0.Bcemm1.AWUXoM96","domain":"facebook.com","path":"/","hostOnly":false,"creation":"2019-03-02T11:32:26.466Z","lastAccessed":"2019-03-02T11:32:29.321Z"},{"key":"sb","value":"tGl6XBnL4pCGpyQiCNRmnJE_","domain":"facebook.com","path":"/","hostOnly":false,"creation":"2019-03-02T11:32:26.505Z","lastAccessed":"2019-03-02T11:32:29.321Z"},{"key":"datr","value":"tGl6XBMHECkwcQqMPipRNPjO","domain":"facebook.com","path":"/","hostOnly":false,"creation":"2019-03-02T11:32:26.507Z","lastAccessed":"2019-03-02T11:32:29.321Z"},{"key":"c_user","value":"100019246754708","domain":"facebook.com","path":"/","hostOnly":false,"creation":"2019-03-02T11:32:26.508Z","lastAccessed":"2019-03-02T11:32:29.321Z"},{"key":"xs","value":"28%3A1JrL26ScxldxDg%3A2%3A1551526325%3A-1%3A-1","domain":"facebook.com","path":"/","hostOnly":false,"creation":"2019-03-02T11:32:26.509Z","lastAccessed":"2019-03-02T11:32:29.321Z"},{"key":"pl","value":"n","domain":"facebook.com","path":"/","hostOnly":false,"creation":"2019-03-02T11:32:26.510Z","lastAccessed":"2019-03-02T11:32:29.321Z"},{"key":"spin","value":"r.4814671_b.trunk_t.1551526326_s.1_v.2_","domain":"facebook.com","path":"/","hostOnly":false,"creation":"2019-03-02T11:32:26.511Z","lastAccessed":"2019-03-02T11:32:29.321Z"},{"key":"presence","value":"EDvF3EtimeF1551526348EuserFA21B19246754708A2EstateFDutF0Et2F_5b_5dElm2FnullEuct2F1551526348470EtrFnullEtwF2342382920EatF1551526348470CEchFDp_5f1B19246754708F0CC","domain":"facebook.com","path":"/","secure":true,"hostOnly":false,"creation":"2019-03-02T11:32:26.511Z","lastAccessed":"2019-03-02T11:32:29.321Z"},{"key":"locale","value":"en_US","domain":"facebook.com","path":"/","secure":true,"hostOnly":false,"creation":"2019-03-02T11:32:26.512Z","lastAccessed":"2019-03-02T11:32:29.321Z"},{"key":"a11y","value":"%7B%22sr%22%3A0%2C%22sr-ts%22%3A1551526348474%2C%22jk%22%3A0%2C%22jk-ts%22%3A1551526348474%2C%22kb%22%3A0%2C%22kb-ts%22%3A1551526348474%2C%22hcm%22%3A0%2C%22hcm-ts%22%3A1551526348474%7D","domain":"facebook.com","path":"/","secure":true,"hostOnly":false,"creation":"2019-03-02T11:32:26.513Z","lastAccessed":"2019-03-02T11:32:29.321Z"},{"key":"fr","value":"1PMyQ4YIXqlcYHpe8.AWVlBphkuKR-Bbsplvl-cYfqYBU.Bcemm0.NV.AAA.0.0.Bcemm1.AWUXoM96","domain":"facebook.com","path":"/","hostOnly":false,"creation":"2019-03-02T11:32:26.466Z","lastAccessed":"2019-03-02T11:32:29.321Z"},{"key":"sb","value":"tGl6XBnL4pCGpyQiCNRmnJE_","domain":"facebook.com","path":"/","hostOnly":false,"creation":"2019-03-02T11:32:26.505Z","lastAccessed":"2019-03-02T11:32:29.321Z"},{"key":"datr","value":"tGl6XBMHECkwcQqMPipRNPjO","domain":"facebook.com","path":"/","hostOnly":false,"creation":"2019-03-02T11:32:26.507Z","lastAccessed":"2019-03-02T11:32:29.321Z"},{"key":"c_user","value":"100019246754708","domain":"facebook.com","path":"/","hostOnly":false,"creation":"2019-03-02T11:32:26.508Z","lastAccessed":"2019-03-02T11:32:29.321Z"},{"key":"xs","value":"28%3A1JrL26ScxldxDg%3A2%3A1551526325%3A-1%3A-1","domain":"facebook.com","path":"/","hostOnly":false,"creation":"2019-03-02T11:32:26.509Z","lastAccessed":"2019-03-02T11:32:29.321Z"},{"key":"pl","value":"n","domain":"facebook.com","path":"/","hostOnly":false,"creation":"2019-03-02T11:32:26.510Z","lastAccessed":"2019-03-02T11:32:29.321Z"},{"key":"spin","value":"r.4814671_b.trunk_t.1551526326_s.1_v.2_","domain":"facebook.com","path":"/","hostOnly":false,"creation":"2019-03-02T11:32:26.511Z","lastAccessed":"2019-03-02T11:32:29.321Z"},{"key":"presence","value":"EDvF3EtimeF1551526348EuserFA21B19246754708A2EstateFDutF0Et2F_5b_5dElm2FnullEuct2F1551526348470EtrFnullEtwF2342382920EatF1551526348470CEchFDp_5f1B19246754708F0CC","domain":"facebook.com","path":"/","secure":true,"hostOnly":false,"creation":"2019-03-02T11:32:26.511Z","lastAccessed":"2019-03-02T11:32:29.321Z"},{"key":"locale","value":"en_US","domain":"facebook.com","path":"/","secure":true,"hostOnly":false,"creation":"2019-03-02T11:32:26.512Z","lastAccessed":"2019-03-02T11:32:29.321Z"},{"key":"a11y","value":"%7B%22sr%22%3A0%2C%22sr-ts%22%3A1551526348474%2C%22jk%22%3A0%2C%22jk-ts%22%3A1551526348474%2C%22kb%22%3A0%2C%22kb-ts%22%3A1551526348474%2C%22hcm%22%3A0%2C%22hcm-ts%22%3A1551526348474%7D","domain":"facebook.com","path":"/","secure":true,"hostOnly":false,"creation":"2019-03-02T11:32:26.513Z","lastAccessed":"2019-03-02T11:32:29.321Z"},{"key":"fr","value":"1PMyQ4YIXqlcYHpe8.AWVlBphkuKR-Bbsplvl-cYfqYBU.Bcemm0.NV.AAA.0.0.Bcemm1.AWUXoM96","domain":"messenger.com","path":"/","hostOnly":false,"creation":"2019-03-02T11:32:26.522Z","lastAccessed":"2019-03-02T11:32:29.322Z"},{"key":"sb","value":"tGl6XBnL4pCGpyQiCNRmnJE_","domain":"messenger.com","path":"/","hostOnly":false,"creation":"2019-03-02T11:32:26.525Z","lastAccessed":"2019-03-02T11:32:29.322Z"},{"key":"c_user","value":"100019246754708","domain":"messenger.com","path":"/","hostOnly":false,"creation":"2019-03-02T11:32:26.526Z","lastAccessed":"2019-03-02T11:32:29.322Z"},{"key":"xs","value":"28%3A1JrL26ScxldxDg%3A2%3A1551526325%3A-1%3A-1","domain":"messenger.com","path":"/","hostOnly":false,"creation":"2019-03-02T11:32:26.527Z","lastAccessed":"2019-03-02T11:32:29.322Z"},{"key":"pl","value":"n","domain":"messenger.com","path":"/","hostOnly":false,"creation":"2019-03-02T11:32:26.529Z","lastAccessed":"2019-03-02T11:32:29.322Z"},{"key":"spin","value":"r.4814671_b.trunk_t.1551526326_s.1_v.2_","domain":"messenger.com","path":"/","hostOnly":false,"creation":"2019-03-02T11:32:26.530Z","lastAccessed":"2019-03-02T11:32:29.322Z"},{"key":"presence","value":"EDvF3EtimeF1551526348EuserFA21B19246754708A2EstateFDutF0Et2F_5b_5dElm2FnullEuct2F1551526348470EtrFnullEtwF2342382920EatF1551526348470CEchFDp_5f1B19246754708F0CC","domain":"messenger.com","path":"/","secure":true,"hostOnly":false,"creation":"2019-03-02T11:32:26.531Z","lastAccessed":"2019-03-02T11:32:29.322Z"},{"key":"locale","value":"en_US","domain":"messenger.com","path":"/","secure":true,"hostOnly":false,"creation":"2019-03-02T11:32:26.532Z","lastAccessed":"2019-03-02T11:32:29.322Z"}]